cachecow/__init__.py
cachecow/mongo.py
cachecow-0.1.3.dist-info/LICENSE
cachecow-0.1.3.dist-info/METADATA
cachecow-0.1.3.dist-info/WHEEL
cachecow-0.1.3.dist-info/top_level.txt
cachecow-0.1.3.dist-info/zip-safe
cachecow-0.1.3.dist-info/RECORD
