Metadata-Version: 2.1
Name: cachecow
Version: 0.1.3
Summary: Fast and simple scaffolding for caching objects in Redis
Home-page: http://github.com/closeio/cachecow
Author: Stefan Wojcik
Author-email: engineering@close.io
Maintainer: Stefan Wojcik
Maintainer-email: engineering@close.io
License: MIT
Platform: any
Classifier: Development Status :: 4 - Beta
Classifier: Intended Audience :: Developers
Classifier: License :: OSI Approved :: MIT License
Classifier: Operating System :: OS Independent
Classifier: Programming Language :: Python
Classifier: Topic :: Software Development :: Libraries :: Python Modules
